l10n_ar_api/__init__.py
l10n_ar_api/afip_webservices/__init__.py
l10n_ar_api/afip_webservices/config.py
l10n_ar_api/afip_webservices/ws_sr_padron/__init__.py
l10n_ar_api/afip_webservices/ws_sr_padron/ws_sr_padron.py
l10n_ar_api/afip_webservices/wsaa/__init__.py
l10n_ar_api/afip_webservices/wsaa/certificate.py
l10n_ar_api/afip_webservices/wsaa/tokens.py
l10n_ar_api/afip_webservices/wsaa/wsaa.py
l10n_ar_api/afip_webservices/wsbfe/__init__.py
l10n_ar_api/afip_webservices/wsbfe/error.py
l10n_ar_api/afip_webservices/wsbfe/invoice.py
l10n_ar_api/afip_webservices/wsbfe/wsbfe.py
l10n_ar_api/afip_webservices/wsct/__init__.py
l10n_ar_api/afip_webservices/wsct/error.py
l10n_ar_api/afip_webservices/wsct/invoice.py
l10n_ar_api/afip_webservices/wsct/wsct.py
l10n_ar_api/afip_webservices/wsfe/__init__.py
l10n_ar_api/afip_webservices/wsfe/error.py
l10n_ar_api/afip_webservices/wsfe/invoice.py
l10n_ar_api/afip_webservices/wsfe/qr_generator.py
l10n_ar_api/afip_webservices/wsfe/wsfe.py
l10n_ar_api/afip_webservices/wsfex/__init__.py
l10n_ar_api/afip_webservices/wsfex/error.py
l10n_ar_api/afip_webservices/wsfex/invoice.py
l10n_ar_api/afip_webservices/wsfex/wsfex.py
l10n_ar_api/afip_webservices/wstesimbrefiscal/__init__.py
l10n_ar_api/afip_webservices/wstesimbrefiscal/error.py
l10n_ar_api/afip_webservices/wstesimbrefiscal/wstesimbrefiscal.py
l10n_ar_api/anmat_webservices/__init__.py
l10n_ar_api/anmat_webservices/anmat.py
l10n_ar_api/anmat_webservices/config.py
l10n_ar_api/arba_webservices/__init__.py
l10n_ar_api/arba_webservices/config.py
l10n_ar_api/arba_webservices/iibb.py
l10n_ar_api/arba_webservices/cot/__init__.py
l10n_ar_api/arba_webservices/cot/config.py
l10n_ar_api/arba_webservices/cot/cot.py
l10n_ar_api/documents/__init__.py
l10n_ar_api/documents/invoice.py
l10n_ar_api/documents/tax.py
l10n_ar_api/documents/tribute.py
l10n_ar_api/documents/tests/__init__.py
l10n_ar_api/documents/tests/test_gross_income.py
l10n_ar_api/documents/tests/test_profit.py
l10n_ar_api-2.12.0.dist-info/METADATA
l10n_ar_api-2.12.0.dist-info/WHEEL
l10n_ar_api-2.12.0.dist-info/top_level.txt
l10n_ar_api-2.12.0.dist-info/RECORD
